vesselasid
